bk_job_xethhung12/_AzBK.py
bk_job_xethhung12/__init__.py
bk_job_xethhung12/__main__.py
bk_job_xethhung12/_module_backup.py
bk_job_xethhung12/_module_log_config.py
bk_job_xethhung12/_cmd/run.py
bk_job_xethhung12-0.0.1.dist-info/METADATA
bk_job_xethhung12-0.0.1.dist-info/WHEEL
bk_job_xethhung12-0.0.1.dist-info/entry_points.txt
bk_job_xethhung12-0.0.1.dist-info/licenses/LICENSE
bk_job_xethhung12-0.0.1.dist-info/RECORD
