Metadata-Version: 2.4
Name: bk_job_xethhung12
Version: 0.0.1
Summary: A command-line tool to back up local files to Azure Blob Storage, using credentials securely fetched from HashiCorp Vault.
Project-URL: Homepage, https://github.com/pypa/sampleproject
Project-URL: Issues, https://github.com/pypa/sampleproject/issues
Author-email: Xeth Hung <admin@xethh.me>
License-Expression: GPL-3.0-only
License-File: LICENSE
Classifier: Operating System :: OS Independent
Classifier: Programming Language :: Python :: 3
Requires-Python: >=3.11
Requires-Dist: j-vault-http-client-xethhung12>=0.1.1
